tppt/__init__.py
tppt/_features.py
tppt/exception.py
tppt/py.typed
tppt/pptx/__init__.py
tppt/pptx/action.py
tppt/pptx/converter.py
tppt/pptx/notes_slide.py
tppt/pptx/presentation.py
tppt/pptx/slide.py
tppt/pptx/slide_layout.py
tppt/pptx/slide_master.py
tppt/pptx/tree.py
tppt/pptx/chart/__init__.py
tppt/pptx/chart/chart.py
tppt/pptx/dml/__init__.py
tppt/pptx/dml/color.py
tppt/pptx/dml/effect.py
tppt/pptx/dml/fill.py
tppt/pptx/dml/line.py
tppt/pptx/enum/__init__.py
tppt/pptx/enum/dml.py
tppt/pptx/shape/__init__.py
tppt/pptx/shape/background.py
tppt/pptx/shape/picture.py
tppt/pptx/shape/placeholder.py
tppt/pptx/shape/text.py
tppt/pptx/table/__init__.py
tppt/pptx/table/cell.py
tppt/pptx/table/table.py
tppt/pptx/text/__init__.py
tppt/pptx/text/font.py
tppt/pptx/text/hyperlink.py
tppt/pptx/text/paragraph.py
tppt/pptx/text/run.py
tppt/pptx/text/text_frame.py
tppt/template/__init__.py
tppt/template/default.py
tppt/template/slide_layout.py
tppt/template/slide_master.py
tppt/tool/__init__.py
tppt/tool/ppt2template.py
tppt/tool/ppt2tree.py
tppt/types/__init__.py
tppt/types/_angle.py
tppt/types/_color.py
tppt/types/_length.py
tppt-0.2.2.dist-info/METADATA
tppt-0.2.2.dist-info/WHEEL
tppt-0.2.2.dist-info/RECORD
