Metadata-Version: 2.4
Name: tppt
Version: 0.2.2
Summary: Typed Python PowerPoint Tool
Project-URL: Documentation, https://yassun7010.github.io/tppt/
Project-URL: Homepage, https://github.com/yassun7010/tppt
Author-email: yassun7010 <yassun7010@outlook.com>
Classifier: Development Status :: 3 - Alpha
Classifier: Intended Audience :: Developers
Classifier: License :: OSI Approved :: MIT License
Classifier: Programming Language :: Python :: 3
Classifier: Programming Language :: Python :: 3.11
Classifier: Programming Language :: Python :: 3.12
Classifier: Programming Language :: Python :: 3.13
Classifier: Programming Language :: Python :: 3.14
Classifier: Topic :: Office/Business :: Office Suites
Classifier: Topic :: Software Development :: Libraries :: Python Modules
Classifier: Typing :: Typed
Requires-Python: >=3.11.0
Requires-Dist: pillow>=10.0.1
Requires-Dist: python-pptx>=1.0.2
Requires-Dist: typing-extensions>=4.13.2
Provides-Extra: pandas
Requires-Dist: pandas>=2.0.0; extra == 'pandas'
Provides-Extra: polars
Requires-Dist: polars>=0.20.0; extra == 'polars'
Provides-Extra: pydantic
Requires-Dist: pydantic>=2.0.0; extra == 'pydantic'
Provides-Extra: tool
Requires-Dist: rich-argparse>=1.7.0; extra == 'tool'
Requires-Dist: rich>=14.0.0; extra == 'tool'
